<journal>
<header><title>Stocks vs. Bonds</title><date>2002-07-17</date></header>
<entry>
<p>An <a href="http://www.forbes.com/forbes/2002/0722/194_print.html">article</a> in Forbes raises some questions about the old argument that historically stocks have done better than bonds, or at least about the future applicability of that argument. Turns out that most of the historical advantage accrued because stocks used to pay healthy dividends -- and those days are over. This could have major implications for investing strategies.</p>
</entry>
</journal>
