<journal>
<header><title>The Crucible</title><date>2003-06-07</date></header>
<entry>
<p>Thanks to <a href="http://avoyagetoarcturus.blogspot.com/">Jay Manifold</a>, I just found <a href="http://www.kansascity.com/mld/kansascitystar/news/opinion/5877654.htm">this editorial</a> about the phenomenon of American Islam: the mixing of Islamic peoples from all over the world (including many African-Americans converts) seems to be leading to the development of an open, tolerant, pluralistic vision of Islam. A hopeful sign.</p>
</entry>
</journal>
